MPInterfaces-2020.6.19.data/scripts/fabfile.py
MPInterfaces-2020.6.19.data/scripts/mpint
MPInterfaces-2020.6.19.data/scripts/smart_rlaunch.py
mpinterfaces/__init__.py
mpinterfaces/calibrate.py
mpinterfaces/data_processor.py
mpinterfaces/database.py
mpinterfaces/default_logger.py
mpinterfaces/firetasks.py
mpinterfaces/instrument.py
mpinterfaces/interface.py
mpinterfaces/lammps.py
mpinterfaces/measurement.py
mpinterfaces/nanoparticle.py
mpinterfaces/old_transformations.py
mpinterfaces/rest.py
mpinterfaces/transformations.py
mpinterfaces/utils.py
mpinterfaces/mat2d/__init__.py
mpinterfaces/mat2d/preparation.py
mpinterfaces/mat2d/electronic_structure/__init__.py
mpinterfaces/mat2d/electronic_structure/analysis.py
mpinterfaces/mat2d/electronic_structure/startup.py
mpinterfaces/mat2d/electronic_structure/tests/__init__.py
mpinterfaces/mat2d/electronic_structure/tests/test_electronic_structure.py
mpinterfaces/mat2d/friction/__init__.py
mpinterfaces/mat2d/friction/analysis.py
mpinterfaces/mat2d/friction/startup.py
mpinterfaces/mat2d/friction/tests/__init__.py
mpinterfaces/mat2d/friction/tests/test_friction.py
mpinterfaces/mat2d/intercalation/__init__.py
mpinterfaces/mat2d/intercalation/analysis.py
mpinterfaces/mat2d/intercalation/startup.py
mpinterfaces/mat2d/intercalation/tests/__init__.py
mpinterfaces/mat2d/intercalation/tests/test_intercalation.py
mpinterfaces/mat2d/magnetism/__init__.py
mpinterfaces/mat2d/magnetism/analysis.py
mpinterfaces/mat2d/magnetism/startup.py
mpinterfaces/mat2d/pourbaix/__init__.py
mpinterfaces/mat2d/pourbaix/analysis.py
mpinterfaces/mat2d/pourbaix/startup.py
mpinterfaces/mat2d/pourbaix/tests/__init__.py
mpinterfaces/mat2d/pourbaix/tests/test_pourbaix.py
mpinterfaces/mat2d/stability/__init__.py
mpinterfaces/mat2d/stability/analysis.py
mpinterfaces/mat2d/stability/startup.py
mpinterfaces/mat2d/stability/tests/__init__.py
mpinterfaces/mat2d/stability/tests/test_stability.py
mpinterfaces/tests/__init__.py
mpinterfaces/tests/eg_lma.py
MPInterfaces-2020.6.19.dist-info/LICENSE.rst
MPInterfaces-2020.6.19.dist-info/METADATA
MPInterfaces-2020.6.19.dist-info/WHEEL
MPInterfaces-2020.6.19.dist-info/top_level.txt
MPInterfaces-2020.6.19.dist-info/RECORD
