Metadata-Version: 2.1
Name: MPInterfaces
Version: 2020.6.19
Summary: High throughput analysis of interfaces using VASP and Materials Project tools
Home-page: https://github.com/henniggroup/MPInterfaces
Author: Kiran Mathew, Joshua J. Gabriel, Michael Ashton, Arunima K. Singh, Joshua T. Paul, Seve G. Monahan, Richard G. Hennig, Venkata Surya Chaitanya Kolluru
Author-email: joshgabriel92@gmail.com, kmathew@lbl.gov, ashtonmv@gmail.com,kvs.chaitanya@ufl.edu,joshuapaul@ufl.edu
Maintainer: Venkata Surya Chaitanya Kolluru, Joshua T. Paul
Maintainer-email: kvs.chaitanya@ufl.edu,joshuapaul@ufl.edu
License: MIT
Platform: UNKNOWN
Classifier: Programming Language :: Python :: 2.7
Classifier: Programming Language :: Python :: 3
Classifier: Programming Language :: Python :: 3.5
Classifier: Programming Language :: Python :: 3.6
Classifier: Development Status :: 4 - Beta
Classifier: Intended Audience :: Science/Research
Classifier: License :: OSI Approved :: MIT License
Classifier: Operating System :: OS Independent
Classifier: Topic :: Scientific/Engineering
Requires-Dist: FireWorks (>=1.4.0)
Requires-Dist: custodian (>=1.0.1)
Requires-Dist: pymatgen-db (>=0.5.1)
Requires-Dist: ase (>=3.11.0)
Requires-Dist: six
Requires-Dist: pyhull (>=1.5.3)
Requires-Dist: seaborn
Requires-Dist: pyyaml
Requires-Dist: nose
Provides-Extra: babel
Requires-Dist: openbabel ; extra == 'babel'
Requires-Dist: pybel ; extra == 'babel'
Provides-Extra: doc
Requires-Dist: sphinx (>=1.3.1) ; extra == 'doc'
Requires-Dist: sphinx-rtd-theme (>=0.1.8) ; extra == 'doc'
Provides-Extra: remote
Requires-Dist: fabric ; extra == 'remote'
